aeg/__init__.py
aeg/_aegis.abi3.so
aeg/_ciphers.py
aeg/_loader.py
aeg/_typing.py
aeg/aegis128l.py
aeg/aegis128x2.py
aeg/aegis128x4.py
aeg/aegis256.py
aeg/aegis256x2.py
aeg/aegis256x4.py
aeg/aegis_cdef.h
aeg/benchmark.py
aeg/util.py
aeg-0.9.0.dist-info/METADATA
aeg-0.9.0.dist-info/WHEEL
aeg-0.9.0.dist-info/top_level.txt
aeg-0.9.0.dist-info/RECORD
