Metadata-Version: 2.4
Name: aeg
Version: 0.9.0
Summary: AEGIS encryption easy to use Python binding. Wheels for major platforms.
Project-URL: Homepage, https://git.zi.fi/LeoVasanko/aegis-python
Project-URL: Repository, https://github.com/LeoVasanko/aegis-python
Classifier: Development Status :: 5 - Production/Stable
Classifier: Programming Language :: Python :: Implementation :: CPython
Classifier: Operating System :: OS Independent
Classifier: Topic :: Security :: Cryptography
Requires-Python: >=3.10
Requires-Dist: cffi>=2.0.0
